anpseisearch/__init__.py
anpseisearch/searcher.py
anpseisearch-0.1.1.dist-info/licenses/LICENSE
anpseisearch-0.1.1.dist-info/METADATA
anpseisearch-0.1.1.dist-info/WHEEL
anpseisearch-0.1.1.dist-info/top_level.txt
anpseisearch-0.1.1.dist-info/RECORD
